{
	"variants": {
		"stage=0": { "model": "chinjufumod:namako/crack_white" },
		"stage=1": { "model": "chinjufumod:namako/crack_orange" },
		"stage=2": { "model": "chinjufumod:namako/crack_magenta" },
		"stage=3": { "model": "chinjufumod:namako/crack_lightb" },
		"stage=4": { "model": "chinjufumod:namako/crack_yellow" },
		"stage=5": { "model": "chinjufumod:namako/crack_lime" },
		"stage=6": { "model": "chinjufumod:namako/crack_pink" },
		"stage=7": { "model": "chinjufumod:namako/crack_gray" },
		"stage=8": { "model": "chinjufumod:namako/crack_lightg" },
		"stage=9": { "model": "chinjufumod:namako/crack_cyan" },
		"stage=10": { "model": "chinjufumod:namako/crack_purple" },
		"stage=11": { "model": "chinjufumod:namako/crack_blue" },
		"stage=12": { "model": "chinjufumod:namako/crack_brown" },
		"stage=13": { "model": "chinjufumod:namako/crack_green" },
		"stage=14": { "model": "chinjufumod:namako/crack_red" },
		"stage=15": { "model": "chinjufumod:namako/crack_black" }
	}
}
