{
	"variants": {
	"facing=north,stage=1": { "model": "chinjufumod:block/kamoicolor/green_birch1n" },
	"facing=south,stage=1": { "model": "chinjufumod:block/kamoicolor/green_birch1s" },
	"facing=west,stage=1": { "model": "chinjufumod:block/kamoicolor/green_birch1w" },
	"facing=east,stage=1": { "model": "chinjufumod:block/kamoicolor/green_birch1e" },

		"facing=north,stage=2": { "model": "chinjufumod:block/kamoicolor/green_birch2n" },
		"facing=south,stage=2": { "model": "chinjufumod:block/kamoicolor/green_birch2s" },
		"facing=west,stage=2": { "model": "chinjufumod:block/kamoicolor/green_birch2w" },
		"facing=east,stage=2": { "model": "chinjufumod:block/kamoicolor/green_birch2e" },

	"facing=north,stage=3": { "model": "chinjufumod:block/kamoicolor/green_birch3n" },
	"facing=south,stage=3": { "model": "chinjufumod:block/kamoicolor/green_birch3s" },
	"facing=west,stage=3": { "model": "chinjufumod:block/kamoicolor/green_birch3w" },
	"facing=east,stage=3": { "model": "chinjufumod:block/kamoicolor/green_birch3e" },

		"facing=north,stage=4": { "model": "chinjufumod:block/kamoicolor/green_birch4n" },
		"facing=south,stage=4": { "model": "chinjufumod:block/kamoicolor/green_birch4s" },
		"facing=west,stage=4": { "model": "chinjufumod:block/kamoicolor/green_birch4w" },
		"facing=east,stage=4": { "model": "chinjufumod:block/kamoicolor/green_birch4e" }
	}
}
