{
	"variants": {
		"facing=up": { "model": "chinjufumod:lamp/lit_marinelamp" },
		"facing=down": { "model": "chinjufumod:lamp/lit_marinelamp", "x": 180 },
		"facing=north": { "model": "chinjufumod:lamp/lit_marinelamp", "x": 270, "y": 180 },
		"facing=south": { "model": "chinjufumod:lamp/lit_marinelamp", "x": 270, "y": 0 },
		"facing=west": { "model": "chinjufumod:lamp/lit_marinelamp", "x": 270, "y": 90 },
		"facing=east": { "model": "chinjufumod:lamp/lit_marinelamp", "x": 270, "y": 270 }
	}
}
